swahilinlp/__init__.py
swahilinlp-0.1.3.dist-info/METADATA
swahilinlp-0.1.3.dist-info/WHEEL
swahilinlp-0.1.3.dist-info/top_level.txt
swahilinlp-0.1.3.dist-info/RECORD
